[
{"fName":"Playground"},
{"fName":"Hiking"},
{"fName":"Restrooms"},
{"fName":"Toddler Playground"},
{"fName":"Spray Park"},
{"fName":"Baseball Field"},
{"fName":"Soccer Field"},
{"fName":"Disabled Access"},
{"fName":"Access Fee"},
{"fName":"Boat Launch"},
{"fName":"Concessions"},
{"fName":"Lake"},
{"fName":"Fishing"},
{"fName":"Walking Trail"},
{"fName":"Beach"},
{"fName":"Tennis Court"},
{"fName":"Disc golf"},
{"fName":"River"},
{"fName":"Pond"},
{"fName":"Basketball Court"},
{"fName":"Boat Rentals"},
{"fName":"Picnic Area"},
{"fName":"Dock Access"},
{"fName":"Multi-Purpose Room Rental"},
{"fName":"Excersize Path"},
{"fName":"Waterfall"},
{"fName":"Skate Park"},
{"fName":"Off Leash Dog Park"},
{"fName":"Lighted Tennis Courts"},
{"fName":"Stream or Creek"},
{"fName":"Bocce Courts"},
{"fName":"Horse Shoe Pits"},
{"fName":"Volleyball"},
{"fName":"Ampitheater"},
{"fName":"Stage"},
{"fName":"Zoo"},
{"fName":"Pool"},
{"fName":"BBQ/Grill"},
{"fName":"Wading Pool"},
{"fName":"Community Garden"},
{"fName":"Covered Picnic Rental"},
{"fName":"Monument/Memorial"},
{"fName":"Museum"},
{"fName":"Community Center"},
{"fName":"Senior Center"},
{"fName":"Football Field"},
{"fName":"Juvenile Fishing"},
{"fName":"Rock Climbing"},
{"fName":"Ice Skating"},
{"fName":"Racquetball"},
{"fName":"Biking/Bike Trail"},
{"fName":"Unmotorized Boat Launch"},
{"fName":"Scuba/Underwater Park"},
{"fName":"Street Hockey"},
{"fName":"Pickle Ball"},
{"fName":"Lacrosse Field"},
{"fName":"Equestrian Trails"},
{"fName":"Handball Court"},
{"fName":"Softball Field"},
{"fName":"Camping"},
{"fName":"Salt Water Fishing"},
{"fName":"Open Grass Area"},
{"fName":"Seasonal Farmers Market"},
{"fName":"Golf Course"},
{"fName":"Tourable Cave"},
{"fName":"Winter/Snow Activities"}
]